swarmbar/__init__.py
swarmbar/swarmbar.py
swarmbar-0.1.0.dist-info/licenses/LICENSE
swarmbar-0.1.0.dist-info/METADATA
swarmbar-0.1.0.dist-info/WHEEL
swarmbar-0.1.0.dist-info/top_level.txt
swarmbar-0.1.0.dist-info/RECORD
