Metadata-Version: 2.4
Name: swarmbar
Version: 0.1.0
Summary: SwarmBar: Bar plots with individual points and significance markers.
Author-email: Neal W Morton <mortonne@gmail.com>
License: BSD 3-Clause License
Project-URL: project, https://github.com/mortonne/swarmbar
Keywords: plotting,visualization,statistics
Classifier: Programming Language :: Python :: 3
Classifier: License :: OSI Approved :: BSD License
Classifier: Operating System :: OS Independent
Requires-Python: >=3.9
License-File: LICENSE
Requires-Dist: numpy
Requires-Dist: matplotlib
Requires-Dist: seaborn>=0.13.0
Dynamic: license-file
